openinference/instrumentation/openai_agents/__init__.py
openinference/instrumentation/openai_agents/_processor.py
openinference/instrumentation/openai_agents/package.py
openinference/instrumentation/openai_agents/py.typed
openinference/instrumentation/openai_agents/version.py
openinference_instrumentation_openai_agents-1.3.1.dist-info/METADATA
openinference_instrumentation_openai_agents-1.3.1.dist-info/WHEEL
openinference_instrumentation_openai_agents-1.3.1.dist-info/entry_points.txt
openinference_instrumentation_openai_agents-1.3.1.dist-info/licenses/LICENSE
openinference_instrumentation_openai_agents-1.3.1.dist-info/RECORD
